[
  {
    "科学家": "屠呦呦",
    "句子编号": 4,
    "句子": "林达尔面带微笑,先后用瑞典语、英语宣布, 2015年诺贝尔生理学或医学奖授予中国药学家屠 呦呦以及爱尔兰科学家威廉姆 坎贝尔和日本科学 家大村智,以表彰他们在寄生虫疾病治疗研究方面 取得的成就",
    "情感得分": -1.0
  },
  {
    "科学家": "屠呦呦",
    "句子编号": 18,
    "句子": "成百上千次反复的尝试,枯燥、寂寞,没有 非凡的毅力、崇高的理想就不可能战胜失败的迷 茫,就不可能找到突破口,也就不可能获得非凡的 成 就",
    "情感得分": -1.0
  },
  {
    "科学家": "屠呦呦",
    "句子编号": 60,
    "句子": "身处天一阁中,抚摸刻有岁月痕迹的廊柱,行 走在绿荫葱葱的院落中,嗅闻浓浓书香,其实也是 回顾中国文化保存和流传的艰辛历程",
    "情感得分": -1.0
  },
  {
    "科学家": "屠呦呦",
    "句子编号": 86,
    "句子": "这在当时的经 济学界、金融界也爆发了一场有关白银问题与改革 币制的大讨论",
    "情感得分": -1.0
  },
  {
    "科学家": "屠呦呦",
    "句子编号": 104,
    "句子": "右为照片背后的赠语:呦妹:学问是无止境的,所以当你局部 成功的时候,你千万不要认为满足,当你不幸失败的时候,你亦千万不要因此灰心",
    "情感得分": -0.3333
  },
  {
    "科学家": "屠呦呦",
    "句子编号": 105,
    "句子": "呦呦,学问决不能 使诚心求她的人失望",
    "情感得分": -1.0
  },
  {
    "科学家": "屠呦呦",
    "句子编号": 108,
    "句子": "这一 年,16岁的屠呦呦经受了 一场 少年屠呦呦 灾难的考验她不幸染上了肺结核,被迫终止了 学业",
    "情感得分": -1.0
  },
  {
    "科学家": "屠呦呦",
    "句子编号": 113,
    "句子": "医 药的作用很神奇,我当时就想,如果我学会了,不 仅可以让自己远离病痛,还可以救治更多人,何乐 而不为呢? 一代药学家的原始起点,就是来自于这种治 己救人的朴素愿望",
    "情感得分": -1.0
  },
  {
    "科学家": "屠呦呦",
    "句子编号": 141,
    "句子": "照片背后题语:盛开的菜花田中 印上了我们的足迹 屠呦呦传 1950年,读高中时的屠 呦呦 其他同学都能像屠呦呦一样勤学好问,认真听讲, 我即使再辛苦也开心! 屠呦呦自己说,那时的我很文静、很低调",
    "情感得分": -1.0
  },
  {
    "科学家": "屠呦呦",
    "句子编号": 154,
    "句子": "为何要学药?则是因为她觉得,用药正 是治疗疾病的主要手段",
    "情感得分": -1.0
  },
  {
    "科学家": "屠呦呦",
    "句子编号": 219,
    "句子": "女儿李军也很长时间里无法理解,母亲怎么能 为了科研、为了事业,就可以舍弃自己的家庭,连 孩子也不顾不上照顾? 每次都颇为陌生的母女相会,也让屠呦呦 暗暗怀疑过自己当初的选择",
    "情感得分": -1.0
  },
  {
    "科学家": "屠呦呦",
    "句子编号": 237,
    "句子": "1950年曾将审查不合格的1355人通知由专署考试, 由于没有充分考虑许多中医提出的缓期考试的 第二章 向医而行 20世纪50年代的毛泽东 要求,结果报考者仅727人,有327人没有通过, 这更引起一些中医的不满",
    "情感得分": -1.0
  },
  {
    "科学家": "屠呦呦",
    "句子编号": 275,
    "句子": "523办公室负责人专程来到中医研究院,开 诚布公地说:中药抗疟已做了好多工作,到流行 地调查,曾收集验秘方来试验,有的有一定效果但 不满意,用法、制剂等方面也存在问题",
    "情感得分": -1.0
  },
  {
    "科学家": "屠呦呦",
    "句子编号": 279,
    "句子": "发起 病来一会高烧焚身,一会如坠冰窟,颤抖不止 疟疾也是军队行动的无形杀手,在古今中外的 每干人宪疾发病率 >100 50-100 10-50 1-10 0.1-1 0-0.1 不存在疟疾 缺少数据 Source:Nalionad mohrni oouto/progpornie rpotu 2013年有疟疾传播的国家和地区 战争史中,因疟疾流行 造成部队严重减员,从 而导致军事行动失败的 战例,时有记载",
    "情感得分": -1.0
  },
  {
    "科学家": "屠呦呦",
    "句子编号": 299,
    "句子": "在革命战争时期曾感染过疟疾、深知其害的 毛泽东回答说:解决你们的问题,也是解决我们的 问题",
    "情感得分": -1.0
  },
  {
    "科学家": "屠呦呦",
    "句子编号": 300,
    "句子": "应越共的请求,毛泽东、周恩来指示,有关部 门要把解决热带地区部队受疟疾侵害,严重影响部 队战斗力,影响军事行动的问题作为一项紧急援 外、战备任务立项",
    "情感得分": -1.0
  },
  {
    "科学家": "屠呦呦",
    "句子编号": 319,
    "句子": "毛泽东所言的解决你们的问题,也是解决我 们的问题,现在看来,这句话含义深刻",
    "情感得分": -1.0
  },
  {
    "科学家": "屠呦呦",
    "句子编号": 320,
    "句子": "在那个 时期,疟疾问题已属于内忧外患,到了非解决 不可的地步",
    "情感得分": -1.0
  },
  {
    "科学家": "屠呦呦",
    "句子编号": 332,
    "句子": "说是课题组,在最初的阶段,屠呦呦只是光 杆司令,只有她一个人孤独地踏上了寻药之路",
    "情感得分": -1.0
  },
  {
    "科学家": "屠呦呦",
    "句子编号": 338,
    "句子": "然即:档定、贵州,云油、广回期 备施各地肉有配其宅前治屿:(1) 肯背三带 麻沙概三雨(又名 混芝廉)水激联指护效俱 好(广目) (2)清青做( 四 川 ) 3 ( 背 三 龄 能 平 三 能 水 霜 数 ( 临 建 ) : ( 膺 游 心一把 生蔡三块岛警少许 前二西捣汁,领忘镑(描 涎 ) ; (6方高八喝,具姆人经共丸 如招子大 启发前四五小时最 二十(刷)(唐站四南, 两偿三蜂快局寝二雨,研麒 泉 保吹三绫,于启发前二小 财整消途下(湖角)i7 皆 一两,感瓜叶三原,马领草二 脚 官检二两,九指子大,邻 4+(0+ 0000011 次服三终(广西)108) 蜜 五 级 浙 员 三 染, 检一趋,开束,分二 吹水酒党屉(红西); V1 惰需六鱼,草果缝率, 高梅三位,骨皮经半, 水应敲(福嚏):0分 鸢四网,地骨皮四, 卑画停二而,单不快叶 设炭十脐*水蘸(广西 就 ) 3 0 育 鸽 尖 一 鱼 , 成单草一染,火药一分, 够 婴 一 个 婚 吃 ( 云 动 ) ; 常三鲶岛银单三 绘)路边金三烧,论虎 剩三能,蛇送三寸,水 激尤要汁,拍发育融t 糊泉)50黄需尖 一龚, 画妆于皮一能鲸子叶 尖 一 绕,亚冰柏实 一 大幕一 水应额(云 南 ) 补方:女叶一里五网 用注:群锦汁泉或澳~溶泉 18~ 1969年4月,《疟疾单秘验方集》封面与其中有关青蒿的内容 常山碱致呕吐的副作用问题,才是屠呦呦工作的重 点",
    "情感得分": -1.0
  },
  {
    "科学家": "屠呦呦",
    "句子编号": 351,
    "句子": "他们期盼着能有所 收获,但结果令人失望 筛选过的中药里,对疟原虫的抑制率最高的也 只有40%左右",
    "情感得分": -1.0
  },
  {
    "科学家": "屠呦呦",
    "句子编号": 355,
    "句子": "这抓住了问题的关键温度正是青蒿素提取 的关键",
    "情感得分": -1.0
  },
  {
    "科学家": "屠呦呦",
    "句子编号": 368,
    "句子": "这是在190次的失败后,大家再一 次严格按照流程进行着筛选",
    "情感得分": -1.0
  },
  {
    "科学家": "屠呦呦",
    "句子编号": 380,
    "句子": "乙醚中性提取物有了,但在进行临床前试验 时,却出现了问题,在个别动物的病理切片中,发 屠呦呦传 现了疑似的毒副作用",
    "情感得分": -1.0
  },
  {
    "科学家": "屠呦呦",
    "句子编号": 381,
    "句子": "经过几次动物试验,疑似问题仍然未能定论",
    "情感得分": -1.0
  },
  {
    "科学家": "屠呦呦",
    "句子编号": 386,
    "句子": "在当时环境下做这样的工作一定极其艰难, 科学家用自己来做实验,这是一种献身精神",
    "情感得分": -2.2
  },
  {
    "科学家": "屠呦呦",
    "句子编号": 437,
    "句子": "1973年第二季度,进行了青蒿素的一系列安全 性试验研究:青蒿素试验剂量无论大或小,对猫的 血压、心率、心律和心电均无明显影响;三批次犬 的毒性试验,除个别犬出现流涎、呕吐和腹泻外, 其他各项指标均正常,未发现明显毒副作用",
    "情感得分": -1.0
  },
  {
    "科学家": "屠呦呦",
    "句子编号": 453,
    "句子": "消息经电话传回北京,大家都十分意外, 一连 串的疑问困扰着屠呦呦和她的团队",
    "情感得分": -1.0
  },
  {
    "科学家": "屠呦呦",
    "句子编号": 521,
    "句子": "举国体制在当年困难的条件下发挥了极大作 用,这种团队精神永远不会过时! 青蒿素的研究历程与成果表明,寻找疟疾治疗 药物的523项目是在文革这一特殊历史时 期,举全国科技之力协作的一个科研项目",
    "情感得分": -1.0
  },
  {
    "科学家": "屠呦呦",
    "句子编号": 541,
    "句子": "高 疟区多是偏远地区,自然条件恶劣,生活条件艰 苦",
    "情感得分": -1.0
  },
  {
    "科学家": "屠呦呦",
    "句子编号": 545,
    "句子": "工作组闯过了生活关爬山关怕蛇 第四章 中国神药 关等各类困难",
    "情感得分": -1.0
  },
  {
    "科学家": "屠呦呦",
    "句子编号": 555,
    "句子": "但是国内的研究条 件非常艰苦",
    "情感得分": -2.0
  },
  {
    "科学家": "屠呦呦",
    "句子编号": 565,
    "句子": "20世纪六七十年代,科研条件还十分艰苦",
    "情感得分": -1.8
  },
  {
    "科学家": "屠呦呦",
    "句子编号": 570,
    "句子": "第四章 中国神药 青蒿济世 疟疾,与艾滋病和癌症一起,被世界卫生组织 列为世界三大死亡疾病之一",
    "情感得分": -1.0
  },
  {
    "科学家": "屠呦呦",
    "句子编号": 615,
    "句子": "作 屠呦呦作课题报告 屠呦呦传 1985年2月,屠呦呦在 进行实验 为她的弟子,王满元知道,中医西医之争,屠呦 呦并不关心",
    "情感得分": -1.0
  },
  {
    "科学家": "屠呦呦",
    "句子编号": 658,
    "句子": "瑞典卡罗林斯卡学院在这一天宣布,将2015 年诺贝尔生理学或医学奖授予中国药学家屠呦呦 以及爱尔兰科学家威廉姆 坎贝尔和日本科学家 大村智,表彰他们在寄生虫疾病治疗研究方面取 得的成就",
    "情感得分": -1.0
  },
  {
    "科学家": "屠呦呦",
    "句子编号": 664,
    "句子": "诺贝尔奖评选委员会用价值无法估量来评 价2015年的获奖成果:由寄生虫引发的疾病困扰 了人类几千年,构成重大的全球性健康问题",
    "情感得分": -1.0
  },
  {
    "科学家": "屠呦呦",
    "句子编号": 666,
    "句子": "今年的获 奖者们均研究出了治疗一些最具伤害性的寄生虫 病的革命性疗法,这两项获奖成果为每年数百万 感染相关疾病的人们提供了强有力的治疗新方 式,在改善人类健康和减少患者病痛方面的成果 无法估量",
    "情感得分": -0.3333
  },
  {
    "科学家": "屠呦呦",
    "句子编号": 693,
    "句子": "其实,中医药从来就是中国最有原创优势的科 技领域 东汉时期的张仲景以治疗伤寒病著名,其 中医经典著作《伤寒论》论述了对多种传染性疾病 不同时期的治疗方法,不但书中的方药沿用至今, 其灵活多变的辨证施治方法也奠定了中医临床实践 的基石",
    "情感得分": -1.0
  },
  {
    "科学家": "屠呦呦",
    "句子编号": 697,
    "句子": "公元前369年至1644年的明朝末年,仅正史 记载的疾病大流行就有95次",
    "情感得分": -1.0
  },
  {
    "科学家": "屠呦呦",
    "句子编号": 709,
    "句子": "她表示,经过现代技 第五章 享誉世界 漫画钓鱼:西方新药研发 是从十万个化合物中才有可 能筛选到一个最终能成为上 市药品的化合物,犹如在大 海里钓鱼;而中国中医药有 几千年的积累,现代新药开 发犹如在中医药水缸里 钓鱼 术的提纯和与现代医学相结合,中草药在疾病治疗 方面所取得的成就很了不起",
    "情感得分": -1.0
  },
  {
    "科学家": "屠呦呦",
    "句子编号": 747,
    "句子": "就在青蒿素越来越受到青睐并得到广泛使用 时,屠呦呦的关注点却已转移到青蒿素被滥用以及 疟原虫耐药性问题上",
    "情感得分": -1.0
  },
  {
    "科学家": "屠呦呦",
    "句子编号": 755,
    "句子": "1975年,在进一步部署青蒿研究大会战的 成都会议上,她就曾因此受到批评",
    "情感得分": -1.0
  },
  {
    "科学家": "屠呦呦",
    "句子编号": 758,
    "句子": "而据相关知情人士介绍, 这句带有批评意味的话,针对的对象之一就是屠 屠呦呦传 呦呦及其研究团队",
    "情感得分": -1.0
  },
  {
    "科学家": "屠呦呦",
    "句子编号": 786,
    "句子": "我现在要说的是40年前,在艰苦的环境 呦呦幼传 下,中国科学家努力奋斗从中医药中寻找抗疟新药 的故事",
    "情感得分": -1.0
  },
  {
    "科学家": "屠呦呦",
    "句子编号": 793,
    "句子": "又经过很多次失败后,1971年 附 录 9月,重新设计了提取方法,改用低温提取,用乙 醚回流或冷浸,而后用碱溶液除掉酸性部位的方法 制备样品",
    "情感得分": -1.0
  },
  {
    "科学家": "屠呦呦",
    "句子编号": 818,
    "句子": "但是,当年从在中国已有两 千多年沿用历史的中药青蒿中发掘出青蒿素的历程 却相当艰辛",
    "情感得分": -1.3
  }
]